README.rst
setup.cfg
setup.py
dj/__init__.py
dj.debug.egg-info/PKG-INFO
dj.debug.egg-info/SOURCES.txt
dj.debug.egg-info/dependency_links.txt
dj.debug.egg-info/entry_points.txt
dj.debug.egg-info/namespace_packages.txt
dj.debug.egg-info/not-zip-safe
dj.debug.egg-info/pbr.json
dj.debug.egg-info/requires.txt
dj.debug.egg-info/top_level.txt
dj/debug/__init__.py
dj/debug/builtin.py
dj/debug/decorators.py
dj/debug/log.py
dj/debug/memory.py
dj/debug/sql.py
dj/debug/timing.py
tests/__init__.py
tests/conftest.py
tests/debug.py
tests/settings.py