Metadata-Version: 1.1
Name: dj.debug
Version: 0.0.2
Summary: Debugging tools for django
Home-page: http://github.com/translate/dj.debug
Author: Ryan Northey
Author-email: ryan@synca.io
License: GPL3
Platform: UNKNOWN
Classifier: Development Status :: 4 - Beta
Classifier: Intended Audience :: Developers
Classifier: Programming Language :: Python :: 2.7
Classifier: Topic :: Software Development :: Libraries :: Python Modules
